gradient_accumulator/__init__.py
gradient_accumulator/accumulators.py
gradient_accumulator/agc.py
gradient_accumulator/layers.py
gradient_accumulator/utils.py
gradient_accumulator-0.5.2.dist-info/LICENSE
gradient_accumulator-0.5.2.dist-info/METADATA
gradient_accumulator-0.5.2.dist-info/WHEEL
gradient_accumulator-0.5.2.dist-info/top_level.txt
gradient_accumulator-0.5.2.dist-info/RECORD
