Metadata-Version: 2.1
Name: gradient-accumulator
Version: 0.5.2
Summary: Package for gradient accumulation in TensorFlow
Home-page: https://github.com/andreped/GradientAccumulator
Author: André Pedersen and David Bouget and Javier Pérez de Frutos and Tor-Arne Schmidt Nordmo
Author-email: andrped94@gmail.com
License: UNKNOWN
Platform: UNKNOWN
Classifier: Development Status :: 4 - Beta
Classifier: Intended Audience :: Developers
Classifier: Topic :: Scientific/Engineering :: Artificial Intelligence
Classifier: Programming Language :: Python :: 3.6
Classifier: Programming Language :: Python :: 3.7
Classifier: Programming Language :: Python :: 3.8
Classifier: Programming Language :: Python :: 3.9
Classifier: Programming Language :: Python :: 3.10
Classifier: Programming Language :: Python :: 3.11
Classifier: Programming Language :: Python :: 3.12
Classifier: License :: OSI Approved :: MIT License
Classifier: Operating System :: OS Independent
Requires-Python: >=3.6
Requires-Dist: tensorflow
Requires-Dist: numpy <=1.23.2
Provides-Extra: dev
Requires-Dist: wheel ; extra == 'dev'
Requires-Dist: setuptools ; extra == 'dev'
Requires-Dist: pytest-cov ; extra == 'dev'
Requires-Dist: black ==22.3.0 ; extra == 'dev'
Requires-Dist: isort ==5.10.1 ; extra == 'dev'
Requires-Dist: flake8 ==4.0.1 ; extra == 'dev'
Requires-Dist: tensorflow-datasets <=4.8.2 ; extra == 'dev'
Requires-Dist: protobuf <=3.20 ; extra == 'dev'
